resp_protein_toolkit/__init__.py
resp_protein_toolkit/classic_rffs.py
resp_protein_toolkit/cpp_ext/basic_encoders.cpp
resp_protein_toolkit/cpp_ext/basic_encoders.h
resp_protein_toolkit/cpp_ext/resp_protein_toolkit_ext.cpp
resp_protein_toolkit/cpp_ext/subsmat_tokenizer.cpp
resp_protein_toolkit/cpp_ext/subsmat_tokenizer.h
resp_protein_toolkit/cpp_ext/utilities.cpp
resp_protein_toolkit/cpp_ext/utilities.h
resp_protein_toolkit/directed_evolution/__init__.py
resp_protein_toolkit/directed_evolution/directed_evolution.py
resp_protein_toolkit/encoders.py
resp_protein_toolkit/protein_ml_models/__init__.py
resp_protein_toolkit/protein_ml_models/bytenet_antibody_antigen.py
resp_protein_toolkit/protein_ml_models/bytenet_antibody_only.py
resp_protein_toolkit/protein_toolkits/__init__.py
resp_protein_toolkit/protein_toolkits/generate_pssm_loadfiles.py
resp_protein_toolkit/protein_toolkits/PFASUM11_distmat.npy
resp_protein_toolkit/protein_toolkits/PFASUM11_raw.npy
resp_protein_toolkit/protein_toolkits/PFASUM20_distmat.npy
resp_protein_toolkit/protein_toolkits/PFASUM20_raw.npy
resp_protein_toolkit/protein_toolkits/PFASUM20_standardized.npy
resp_protein_toolkit/protein_toolkits/PFASUM30_distmat.npy
resp_protein_toolkit/protein_toolkits/PFASUM30_raw.npy
resp_protein_toolkit/protein_toolkits/PFASUM30_standardized.npy
resp_protein_toolkit/protein_toolkits/PFASUM62_distmat.npy
resp_protein_toolkit/protein_toolkits/PFASUM62_raw.npy
resp_protein_toolkit/protein_toolkits/PFASUM62_standardized.npy
resp_protein_toolkit/protein_toolkits/PFASUM75_distmat.npy
resp_protein_toolkit/protein_toolkits/PFASUM75_raw.npy
resp_protein_toolkit/protein_toolkits/PFASUM75_standardized.npy
resp_protein_toolkit/protein_toolkits/PFASUM85_distmat.npy
resp_protein_toolkit/protein_toolkits/PFASUM85_raw.npy
resp_protein_toolkit/protein_toolkits/PFASUM85_standardized.npy
resp_protein_toolkit/protein_toolkits/PFASUM90_distmat.npy
resp_protein_toolkit/protein_toolkits/PFASUM90_raw.npy
resp_protein_toolkit-0.2.3.dist-info/METADATA
resp_protein_toolkit-0.2.3.dist-info/WHEEL
resp_protein_toolkit-0.2.3.dist-info/licenses/LICENSE
resp_protein_toolkit-0.2.3.dist-info/RECORD
