Metadata-Version: 2.1
Name: resp_protein_toolkit
Version: 0.2.3
Summary: Basic toolkit for common protein engineering tasks
Keywords: RESP,protein_engineering
Author-Email: Jonathan Parkinson <jlparkinson1@gmail.com>
License: Copyright 2024 The Regents of the University of California San Diego. All Rights Reserved.
Project-URL: Homepage, https://github.com/jlparki/resp_protein_toolkit
Project-URL: Documentation, https://github.com/jlparki/resp_protein_toolkit
Requires-Python: >=3.9
Requires-Dist: numpy
